liteserver/__init__.py
liteserver/liteCNSresolv.py
liteserver/liteserver.py
liteserver/device/__init__.py
liteserver/device/helpers.py
liteserver/device/i2c.py
liteserver/device/liteCNSserver.py
liteserver/device/liteGQ.py
liteserver/device/liteLabjack.py
liteserver/device/liteMCUFEC.py
liteserver/device/litePeakSimulator.py
liteserver/device/liteScaler.py
liteserver/device/liteUSBCam.py
liteserver/device/liteUvcCam.py
liteserver/device/liteVGM.py
liteserver/device/liteWLM.py
liteserver/device/senstation.py
liteserver-3.3.6.dist-info/METADATA
liteserver-3.3.6.dist-info/WHEEL
liteserver-3.3.6.dist-info/RECORD
