Metadata-Version: 2.4
Name: liteserver
Version: 3.3.6
Summary: Lightweight control system for scientific instruments. Resembles EPICS
Project-URL: Homepage, https://github.com/ASukhanov/liteServer
Project-URL: Bug Tracker, https://github.com/ASukhanov/liteServer/issues
Author-email: Andrei Sukhanov <cyxandr@gmail.com>
Classifier: License :: OSI Approved :: MIT License
Classifier: Operating System :: OS Independent
Classifier: Programming Language :: Python :: 3
Requires-Python: >=3.7
Requires-Dist: cbor2
